{"playerSpec":{"currentPlayerLevel":0,"currentPlayerHP":110.0,"currentPlayerEXP":0.0,"currentPlayerAttackPoint":5.0,"currentPlayerCost":3.6296560764312746,"maxPlayerHP":111.0,"maxPlayerEXP":100.0,"maxPlayerAttackPoint":5.0,"maxPlayerCost":13.0,"currentCostIncreaseAmount":1.8000000715255738},"playerEquipment":{"currentHeadEquipID":1094,"currentBodyEquipID":1072,"currentShoesEquipID":1084,"currentWeaponEquipID":1033,"playerHaveEquipmentIDs":[1094,1084,1072,1033,1042,1043,1052,1053],"playerHaveEquipmentCount":[1,1,1,1,1,1,1,1]},"playerCards":{"haveCardIDs":[1,10,9,5,7],"haveCardCounts":[1,2,1,2,1],"deckCardIDs":[1,9,7]},"playerItems":{"playerItemIDs":[2002,2001],"playeItemCount":[8,1]}}